cfel_pylint_checkers/__init__.py
cfel_pylint_checkers/no_direct_dict_access.py
cfel_pylint_checkers/tango_command_dtype.py
cfel_pylint_checkers-1.1.4.dist-info/METADATA
cfel_pylint_checkers-1.1.4.dist-info/WHEEL
cfel_pylint_checkers-1.1.4.dist-info/LICENSE
cfel_pylint_checkers-1.1.4.dist-info/RECORD
