Metadata-Version: 2.1
Name: cfel-pylint-checkers
Version: 1.1.4
Summary: Additional checkers for pylint that are used by the FS-CFEL-1 team
Home-page: https://gitlab.desy.de/cfel-sc-public/cfel-pylint-checkers
License: GPL-3.0-or-later
Author: Philipp Middendorf
Author-email: philipp.middendorf@desy.de
Requires-Python: >=3.8,<3.11
Classifier: License :: OSI Approved :: GNU General Public License v3 or later (GPLv3+)
Classifier: Programming Language :: Python :: 3
Classifier: Programming Language :: Python :: 3.8
Classifier: Programming Language :: Python :: 3.9
Classifier: Programming Language :: Python :: 3.10
Requires-Dist: pylint (>=2.14.0,<3.0.0)
Project-URL: Repository, https://gitlab.desy.de/cfel-sc-public/cfel-pylint-checkers
